Metadata-Version: 2.4
Name: knowledge-base-builder
Version: 0.1.2
Summary: 🚀 Builds a structured markdown knowledge base from external sources such as websites, documents, and GitHub repos with large language models. Ideal for RAG, SEO-friendly LLM contexts (/llms.txt), and chatbots.
Home-page: https://github.com/kostadindev/knowledge-base-builder
Author: Kostadin Devedzhiev
Author-email: kostadin.g.devedzhiev@gmail.com
Project-URL: Homepage, https://github.com/kostadindev/knowledge-base-builder
Project-URL: Documentation, https://github.com/kostadindev/knowledge-base-builder#readme
Classifier: Development Status :: 4 - Beta
Classifier: Intended Audience :: Developers
Classifier: Programming Language :: Python :: 3
Classifier: Programming Language :: Python :: 3.8
Classifier: Programming Language :: Python :: 3.9
Classifier: Programming Language :: Python :: 3.10
Classifier: Programming Language :: Python :: 3.11
Classifier: License :: OSI Approved :: MIT License
Classifier: Operating System :: OS Independent
Classifier: Topic :: Software Development :: Libraries :: Python Modules
Classifier: Topic :: Documentation
Classifier: Topic :: Text Processing :: Markup
Requires-Python: >=3.8
License-File: LICENSE
Requires-Dist: langchain>=0.1.0
Requires-Dist: langchain-google-genai>=0.0.5
Requires-Dist: langchain-community>=0.0.13
Requires-Dist: beautifulsoup4>=4.12.2
Requires-Dist: requests>=2.31.0
Requires-Dist: python-dotenv>=1.0.0
Requires-Dist: lxml>=4.9.3
Requires-Dist: pypdf>=3.17.0
Requires-Dist: python-docx>=0.8.11
Requires-Dist: markdown>=3.4.3
Requires-Dist: mistune>=2.0.5
Requires-Dist: striprtf>=0.0.22
Requires-Dist: pandas>=2.0.0
Requires-Dist: openpyxl>=3.1.2
Requires-Dist: ezodf>=0.3.2
Requires-Dist: pyyaml>=6.0
Dynamic: author
Dynamic: author-email
Dynamic: classifier
Dynamic: description
Dynamic: description-content-type
Dynamic: home-page
Dynamic: license-file
Dynamic: project-url
Dynamic: requires-dist
Dynamic: requires-python
Dynamic: summary
